<document xml:lang="sma" id="no_id"><header><title/><genre code="admin"/><author><unknown/></author><wordcount>134</wordcount><conversion_status type="standard"/><availability><free/></availability><submitter name="Kevin Brubeck Unhammer" email="unhammer@fsfe.org"/><multilingual><language xml:lang="swe"/><language xml:lang="sma"/></multilingual><origFileName>http://www.lansstyrelsen.se/dalarna/SMA/om-lansstyrelsen/vart-uppdrag/Pages/default.aspx</origFileName><parallel_text xml:lang="eng" location="om-lansstyrelsen-vart-uppdrag.html"/><parallel_text xml:lang="swe" location="om-lansstyrelsen-vart-uppdrag.html"/><metadata><uncomplete/></metadata><version>XSLtemplate $Revision$; file-specific xsl  Revision; common.xsl  $Revision$; </version></header><body><p>Mijjen laavenjasse - Länsstyrelsen i Dalarna</p>
<list/><p type="title">Mijjen laavenjasse</p>
<p>Lïeneståvroen laavenjasse lea evtiedimmien barkedh gusnie byjrese, sjædtoeh jïh hijven jielemetsiehkieh siemedieh. Ulmie lea raajnes jielemebyjrese, nænnoes barkoemaarhna jïh aaj hijven jieleme årrojidie. Ånehks jeahteme mijjieh barkebe nænnoes evtiedimmine lïenesne.</p>
<p>Lïeneståvroen dïedte rïjhkebiejjeste jïh reerenasseste mieriedimmieh lïenesne tjïrretieh, jïh mijjieh iktedibie staaten barkoem. Lïenen evtiedimmie edtjebe dovne aktegs almetjen jïh sïebredahken ïedtjh vaarjelidh jïh barkedh.</p>
<p>Mijjieh libie maahtoeorganisasjovne mij dåeresthsektoriellen barkedh jïjnjh ovmessie aamhtesegyhtjelassigujmie. Mijjen maahtoesuerkieh leah ovmessie sïebredahkegyhtjelassh dijpieh ovmessie vuekine, voeneevtiedimmeste jïh biologijen gellielaaketje integrasjovnegyhtjelasside jïh kultuvrebyjresem vaarjelidh.</p>
<p>Lïeneståvroeinsturksjovnen (SFS 2007:825) mietie edtjebe gaskem jeatjabem dejnie barkedh</p>
<list><p type="listitem">beapmoehvaaksjome, juvrevaarjelimmie jïh åålmegi veterinæreles gyhtjelassh</p>
<p type="listitem">regionalen sjædtoe</p>
<p type="listitem">infrastruktuvresoejkesjimmie</p>
<p type="listitem">nænnoes sïebredahkesoejkesjimmieh jïh årrojh</p>
<p type="listitem">energije jïh klimate</p>
<p type="listitem">kultuvrebyjrese</p>
<p type="listitem">ovlæhkoej vööste jïh aaj krijsevuartoe jïh sivilen dåastoelimmie</p>
<p type="listitem">eatnemegeehteme jïh aaj byjrese- jïh healsoevaarjelimmie</p>
<p type="listitem">laanteburrie jïh voene</p>
<p type="listitem">gööleme</p>
<p type="listitem">seammavyörtegs</p>
<p type="listitem">integrasjovne</p>
</list></body></document>
