<document xml:lang="sma" id="no_id"><header><title/><genre code="admin"/><author><unknown/></author><wordcount>380</wordcount><conversion_status type="standard"/><availability><free/></availability><multilingual/><origFileName>http://www.saemiedigkie.no/layout/set/print</origFileName><parallel_text xml:lang="nob" location="print.html"/><parallel_text xml:lang="sme" location="print.html"/><metadata><uncomplete/></metadata><version>XSLtemplate $Revision$; file-specific xsl  Revision; common.xsl  $Revision$; </version></header><body><p>Saemiedigkie - Sametinget</p>
<p><span type="quote">Saemiedigkie edtja saemiej politihkeles sijjiem veaksahbåbpoe darjodh jïh saemiej iedtjh skreejredh Nöörjesne jïh sjïehteladtedh guktie saemieh maehtieh sov gïelem, sov kultuvrem jïh sov siebriedahkejieledem gorredidh jïh evtiedidh.</span></p>
<p>Saemiedigkien bïjre</p>
<p>Veeljeme jïh veeljemelåhkoe</p>
<p>Stipendh jïh dåarjoeh</p>
<p xml:lang="nob">Web-tv</p>
<p xml:lang="myv">`</p>
<list><p type="listitem" xml:lang="sme">Sámedikki lávdegoddečoahkkimat álget vuossárggá guovvamánu 29. b. dii 09.00 ja loahpahuvvojit maŋŋebárgga njukčamánu 1. b. dii. 15.00 rádjái. Dievasčoahkkin álgá gaskavahku guovvamánu 2. b. dii. 09.00 ja loahpahuvvo bearjadaga guovvamánu 4. b. dii. 15.00 rádjái</p>
<p type="listitem" xml:lang="sme">Logo eambbo</p>
<p type="listitem" xml:lang="nob">Web-tv</p>
<p type="listitem" xml:lang="sme">2015 duodješiehtadallamiin gaskal Sámedikki, Duojáriid Ealáhussearvvi ja Sámiid Duodji, šadde ovttamielalaččat dasa ahte árvvoštallat sáhttet go duodjeorganisašuvnnat váldit badjelasas doaibmadoarjaga hálddašeami. Sámediggi oaččui Concis Kárášjoga...</p>
<p type="listitem" xml:lang="sme">Sámedikki presideanta Aili Keskitalo lea ilus go giellalávdegotti oasseraporta lea buktojuvvon. –Mii háliidit ahte raporta buvttihivččii buori ságastallama sámegiela boahtteáiggi hálddašeami birra, dadjá Sámedikki presideanta Aili Keskitalo.</p>
<p type="listitem">Mijjieh daejtie ohtsememieride voerkelibie:</p>
<p type="listitem">Stipende jollebe ööhpehtæmman – Ohtsememierie goevten 1.b.</p>
<p type="listitem">Dåarjoe kultuvremojhtesevaarjelæmman – Ohtsememierie goevten 15.b.</p>
<p type="listitem" xml:lang="sme">Sámediggeráđđi lea dál ovddidan ášši Sámedikki dievasčoahkkimii, dainna ávžžuhusain ahte hilgu ruvkedoaimma plánaid Nussirii ja Gumpenjunnái.</p>
<p type="listitem" xml:lang="nob">Sametinget og Oslo kommune signerer felles samarbeidserklæring lørdag 6. februar i Oslo.</p>
<p type="listitem" xml:lang="fra">Les mer.</p>
<p type="listitem">Saemiedigkieraerie edtja guessine mïnnedh ovmessie voenges siebriedahkine juktie raerieh åadtjodh Saemiedigkien politihkese arealen jïh byjresen sisnjeli. – Mijjieh sïjhtebe saemien tjïerth, siebrieh, jielemebarkijh jïh faagealmetjh voengesne böör...</p>
</list><list/><p>Saemiedigkien bïjre</p>
<p>Tjirkijh</p>
<p>Stoerretjåanghkoe</p>
<p>Saemiedigkieraerie</p>
<p>Tjaatsegh</p>
<p>Biejjielåhkoe</p>
<p>Gaskesadth mijjine</p>
<p>View Saemiedigkien bïjre</p>
<p type="title">Gïele</p>
<p type="title">Bïevnesh saemien gïeli bïjre</p>
<p type="title">Reeremedajve saemien gïelide</p>
<p type="title">Saemien sijjienommh</p>
<p>View Gïele</p>
<p type="title">Kultuvrejieleme</p>
<p type="title">Stipende jïh dåarjoe</p>
<p type="title">Meedijah</p>
<p type="title">Gaarsjelimmie</p>
<p xml:lang="smn">View Kultuvrejieleme</p>
<p type="title">Lïerehtimmie</p>
<p type="title">Maanagïerte</p>
<p type="title">Maadthskuvle jïh Jåa</p>
<p type="title">Dotkeme jïh jollebe ööhpehtimmie</p>
<p>View Lïerehtimmie</p>
<p type="title">Jielemh</p>
<p type="title">Båatsoe</p>
<p type="title">Marijne jielemh</p>
<p type="title">Jåartaburrie</p>
<p xml:lang="smn">View Jielemh</p>
<p type="title">Healsoe jïh sosijaale</p>
<p type="title">Maanavaarjelimmie</p>
<p type="title">Healsoe</p>
<p type="title">Sosijaale</p>
<p>View Healsoe jïh sosijaale</p>
<p type="title">Byjrese, areale jïh kultuvrevarjelimmie</p>
<p type="title">Kultuvremojhtesh</p>
<p type="title">Eatnemegellievoete</p>
<p type="title" xml:lang="ron">Areale</p>
<p>View Byjrese, areale jïh kultuvrevarjelimmie</p>
<p type="title">Laante jïh vierhtiereaktah</p>
<p type="title">Laantereaktah</p>
<p type="title">Göölemereakta</p>
<p type="title">Goerehtalleme</p>
<p>View Laante jïh vierhtiereaktah</p>
<p type="title">Gaskenasjovnaale barkoe</p>
<p type="title">Saemien laavenjostoe</p>
<p type="title">Raastendåaresth regijovnaale laavenjostoe</p>
<p type="title">Gaskenasjovnaale aalkoealmetjelaavenjostoe</p>
<p>View Gaskenasjovnaale barkoe</p>
<p type="title">Politihkeles siebrie</p>
<p>Saemiedigkieraerie</p>
<p>Raerie lea goh Saemiedigkien reerenasse, jïh dam biejjieladtje politihkeles barkoem reerie. Saemiedigkieraerien lïhtsegh leah nammoehtamme presidenteste, mij lea raerien åvtehke.</p>
<p>Stoerretjåanghkoe</p>
<p>Saemiedigkien stoerretjåanghkoe lea Saemiedigkien bijjemes åårgane jïh faamoe. Stoerretjåanghkoeh sïejhmemes njieljien aejkien jaepien, seamma våhkoen goh moenehtsetjåanghkoeh.</p>
<p type="title">Mij heannede?</p>
<p xml:lang="vep">06.03.2016 - 11.03.2016</p>
<p xml:lang="sme">Searvá AWG</p>
<p xml:lang="vep">08.03.2016 - 08.03.2016</p>
<p>Generalforsamling Åarjelhsaemien Teatere</p>
<p xml:lang="vep">10.03.2016 - 10.03.2016</p>
<p xml:lang="nob">Seminar - Joikens frie natur</p>
<p xml:lang="vep">14.03.2016 - 17.03.2016</p>
<p>AIEC2016 öörnesåvva Guovdageaidnusne</p>
<p xml:lang="vep">14.03.2016 - 14.03.2016</p>
<p xml:lang="eng">Violence Against Indigenous Women</p>
<p xml:lang="vep">07.04.2016 - 08.04.2016</p>
<p xml:lang="sme">Bovdehus gielddaseminárii</p>
<p type="title">Gærjagåetie</p>
<p>Gærjagåetie</p>
</body></document>
