<document xml:lang="sma" id="no_id"><header><title/><genre code="admin"/><author><unknown/></author><wordcount>90</wordcount><conversion_status type="standard"/><availability><free/></availability><multilingual/><origFileName>http://www.saemiedigkie.no/layout/set/print/Byjrese-areale-jih-kultuvrevarjelimmie/Energije-jih-mineraalh/Saemiedigkie-luejhtemeluhpiem-laajhta-Nussirese</origFileName><parallel_text xml:lang="nob" location="sametinget-klager-paa-utslippstillatelsen-til-nussir.html"/><parallel_text xml:lang="sme" location="samediggi-vaida-nussira-luoitinlobi.html"/><metadata><uncomplete/></metadata><version>XSLtemplate $Revision$; file-specific xsl  Revision; common.xsl  $Revision$; </version></header><body><p>Saemiedigkie luejhtemeluhpiem laajhta Nussirese / Energije jïh mineraalh / Byjrese, areale jïh kultuvrevarjelimmie / Saemiedigkie - Sametinget</p>
<p type="title">Saemiedigkie luejhtemeluhpiem laajhta Nussirese</p>
<p xml:lang="sme">11. Ođđajagimánnu 2016</p>
<p>Saemiedigkie lea Byjresedirektovraaten nænnoestimmiem laajhteme mij Nussir ASA:se luejhtemeluhpiem vadta gruvabaatsehtsem luejhtedh Repparfjovlen sïjse Kvalsunden tjïeltesne. Laejhtiemisnie birrebe Klijma- jïh byrjesedepartemeente nænnoestimmiem jeatjahtahta, jïh Nussir ASA:n ohtsemem gruvagïehtelimmieluhpien bïjre nyöjhkoe deerjemelaaken mietie gaavnojne Nussir jïh Gumpenjunni/Ulveryggen. Saemiedigkie sæjhta Klijma- jïh byrjesedepartemeentine rååresjidh laejhtemegïetedimmien bïjre.</p>
<p type="title" xml:lang="nob">Klage på vedtak - Tillatelse til virksomhet etter foruresningsloven for Nussir ASA</p>
<p><em type="bold">Vielie bïevnesh: </em></p>
<p>Saemiedigkieraerie Silje Karine Muotka, tell. 984 87 576.</p>
</body></document>
