<document xml:lang="sma" id="no_id"><header><title/><genre code="facta"/><author><unknown/></author><wordcount>930</wordcount><conversion_status type="standard"/><availability><free/></availability><submitter name="Kevin Brubeck Unhammer" email="unhammer+apertium@mm.st"/><multilingual><language xml:lang="swe"/><language xml:lang="sma"/></multilingual><origFileName>http://www.samediggi.se/7548</origFileName><metadata><uncomplete/></metadata><version>XSLtemplate $Revision: 104145 $; file-specific xsl  Revision; common.xsl  $Revision$; </version></header><body><p xml:lang="swe">Ortnamn på sydsamiska - Sametinget</p>
<p>Vägskylt i Tärnaby. Foto: Per-Martin Israelsson.</p>
<p type="title" xml:lang="swe">Sydsamiska ortnamn</p>
<p xml:lang="swe">Denna sydsamiska ortnamnslista är ett urval av ortnamn från svenska områden. Vissa platser ligger inom det umesamiska språkområdet, deras umesamiska namnformer är markerade med SaU -. Med viss reservation kan något namn bli föremål för justering.</p>
<p xml:lang="swe"><em type="italic">Förkortningar för Län </em>Gävleb. = Gävleborgs län N.b. = Norrbotten Stockh. = Stockholm V.b. = Västerbotten V.N. = Västernorrland <em type="italic">Förkortningar för Kommuner </em>Arj. = Arjeplog Arv. = Arvidsjaur Bjurh. = Bjurholm Dor. = Dorotea Härnös. = Härnösand Lycks. = Lycksele Skell. = Skellefteå Sor. = Sorsele Storu. = Storuman Ströms. = Strömsund Sundsv. = Sundsvall Söderh. = Söderhamn Vilh. = Vilhelmina Vind. = Vindeln Åsele = Åsele Östers. = Östersund Ö-vik = Örnsköldsvik Stockh. = Stockholm Åre = Åre </p>
<p><em type="italic">A Aaha </em>/SaU Áhá/ <em type="italic">Aha </em>(Sor. V.b.) <em type="italic">Aahka </em>/SaU Áhkká/ <em type="italic">Akkan </em>(Storu. V.b.) <em type="italic">Aanege </em><em type="italic">Anundsjö </em>(Ö.vik V.n.) <em type="italic">Aanevaartoe </em><em type="italic">Annevare </em>(Vilh. V.b.) <em type="italic">Aarejaevrien gieles, Aaren laedtie </em><em type="italic">Aronsjöliden </em>(Vilh. V.b.) <em type="italic">Aavh-jaevrie </em>/SaU Avjávrrie/ <em type="italic">Ajaur </em>(Lycks. V.b.) <em type="italic">Aavjaevrie </em><em type="italic">Ajaur </em>( <em type="italic">forsen </em>) (Storu. V.b.) <em type="italic">Aavjere </em><em type="italic">Avasjö </em>(Åsele V.b.) <em type="italic">Aavjere </em><em type="italic">Vardofjäll </em>(Vilh. V.b.) <em type="italic">Aavroleps fuersie </em><em type="italic">Krokfors </em>(Storu. V.b.) <em type="italic">Aerviesjaevrie </em>/SaU. Árviesjávrrie/ <em type="italic">Arvidsjaur </em>(Arv. N.b.) <em type="italic">Alkejaevrie </em><em type="italic">Älgsjö </em>(Åsele V.b.) <em type="italic">Almesovvene </em><em type="italic">Almsele </em>(Vilh. V.b.) </p>
<p><em type="italic">B Baavrejaevrie </em><em type="italic">Pauträsk </em>(Storu. V.b.) <em type="italic">Baektiesbierjie, Gïengeles govre </em><em type="italic">Djupdal </em>(Vilh. V.b.) <em type="italic">Baerjege </em><em type="italic">Borgsjö </em>(Åsele V.b.) <em type="italic">Baerniefuersie </em><em type="italic">Gardikfors </em>(Storu. V.b.) <em type="italic">Ballore, Bealloejaevrie </em>/SaU. Bielluojávrrie/ <em type="italic">Ballaren </em>, <em type="italic">Biellojaure </em>(Sor. V.b.) <em type="italic">Barresoene </em>/SaU. Bárjiege/ <em type="italic">Barsele </em>(Storu. V.b.) <em type="italic">Bastanjaevrie </em><em type="italic">Bastansjö </em>(Storu. V.b.) <em type="italic">Beetske </em><em type="italic">Bäsksele </em>(Vilh. V.b.) <em type="italic">Bienjedaelie </em><em type="italic">Funäsdalen </em>(Härje. Jämtl.) <em type="italic">Bïerne </em><em type="italic">Björna </em>(Ö.vik V.n.) <em type="italic">Bietsiejaevrie </em><em type="italic">Tallsjö </em>(Åsele V.b.) <em type="italic">Bijjie Spädtja </em><em type="italic">Vålådalen </em>(Åre Jämtl.) <em type="italic">Blaahnege </em>/SaU Bláhnage, Bláhnagesuvvane/ <em type="italic">Blattniksele </em>(Sor. V.b.) <em type="italic">Buajtahke </em><em type="italic">Bojtiken </em>(Vilh. V.b.) <em type="italic">Buarkantjahke </em><em type="italic">Borgafjäll </em>(Dor. V.b.) <em type="italic">Bååhne </em><em type="italic">Hosjöbotten </em>(Åre Jämtl.) </p>
<p><em type="italic">D Daana </em>/SaU Dáná/ <em type="italic">Danasjö </em>(Storu. V.b.) <em type="italic">Dearna </em><em type="italic">Tärnaby </em>(Storu. V.b.) <em type="italic">Dïeknjehke </em><em type="italic">Tängvattnet </em>(Storu. V.b.) <em type="italic">Derhvedslaedtie </em><em type="italic">Torvsjö </em>(Åsele V.b.) <em type="italic">Digkie-sovvene </em>/SaU Diggie-suvvane/ <em type="italic">Diksele </em>(Sor. V.b.) <em type="italic">Doelteme-jaevrie </em>/SaU Duölddiemejávrrie/ <em type="italic">Kokträsk </em>(Malå V.b.) <em type="italic">Draehkie </em>/SaU Dráhkie/ <em type="italic">Gargnäs </em>(Sor. V.b.) <em type="italic">Dreejhöönine </em><em type="italic">Trehörningssjö </em>(Ö.vik V.n.) <em type="italic">Döörte </em>[Kraapohke, Kraaponjaevrie] <em type="italic">Dorotea </em>[Bergvattnet] (Dor. V.b.) </p>
<p><em type="italic">E Eajra </em><em type="italic">Idre </em>(Älvd. Dal.) <em type="italic">Eejlesvaartoe </em><em type="italic">Heligfjäll </em>(Vilh. V.b.) </p>
<p><em type="italic">F Faahtjere, Feehtjere </em>ee&gt;&lt;ää <em type="italic">Fättjaur </em>(Vilh. V.b.) <em type="italic">Faantse </em>/SaU Fántsa/ <em type="italic">Fansen </em>(Storu. V.b.) <em type="italic">Faepmie </em><em type="italic">Fatmomakke </em>(Vilh. V.b.) <em type="italic">Flïerke </em><em type="italic">Flärke </em>(Ö.vik V.n.) <em type="italic">Frööstege </em><em type="italic">Frostviken </em>(Ströms. Jämtl.) </p>
<p><em type="italic">G Gaallajaevrie </em>/SaU Gállájávrrie/ <em type="italic">Gubbträsk </em>(Storu. V.b.) <em type="italic">Gaelpie </em><em type="italic">Dalasjö </em>(Vilh. V.b.) <em type="italic">Gaertiejaevrie </em>/SaU Gárddiejávrrie/ <em type="italic">Gardsjön </em>(Storu. V.b.) <em type="italic">Gajhrege, Gajhtohke </em><em type="italic">Matsdal </em>(Vilh. V.b.) <em type="italic">Gaskeloekte </em><em type="italic">Gaskeluokt </em>(Storu. V.b.) <em type="italic">Geavtse </em>/SaU Gávtsjávrrie/ <em type="italic">Ammarnäs </em>(Sor. V.b.) <em type="italic">Gïelese </em><em type="italic">Gielas </em>(Vilh. V.b.) <em type="italic">Gierkiesovvene </em>/SaU Geärggiesuvvane/ <em type="italic">Stensele </em>(Storu. V.b.) <em type="italic">Glijre, Klïere </em><em type="italic">Glen </em>(Bergs Jämtl.) <em type="italic">Goerbevaerie </em>/SaU Guorbbavárrie/ <em type="italic">Kurbevare </em>(Malå V.b.) <em type="italic">Graatja </em><em type="italic">Umnäs </em>(Storu. V.b.) <em type="italic">Guhkiesjaevrie </em><em type="italic">Långvattnet </em>(Storu. V.b.) <em type="italic">Gååpsene </em><em type="italic">Gafsele </em>(Åsele V.b.) <em type="italic">Gäjka </em><em type="italic">Dikanäs </em>(Vilh. V.b.) <em type="italic">Gärma </em><em type="italic">Jorm </em>(Frostv. Jämtl.) </p>
<p><em type="italic">H Hïelle </em><em type="italic">Hälla </em>(Åsele V.b.) <em type="italic">Hierkiejaevrie </em>/SaU Heärggiejávrrie/ <em type="italic">Fjällbosjö </em>(Storu. V.b.) <em type="italic">Hïernesaande </em><em type="italic">Härnösand </em>(Härnös. V.n.) </p>
<p><em type="italic">J Jeanoejåakoe </em><em type="italic">Åskilje </em>(Storu. V.b.) <em type="italic">Jïjnjesovvene </em><em type="italic">Storsele </em>(Vilh. V.b.) <em type="italic">Jillie-Laajsere </em><em type="italic">Västansjö </em>(Storu. V.b.) <em type="italic">Jilliesjaevrie </em><em type="italic">Västansjö </em>(Vilh. V.b.) <em type="italic">Jillies loekte </em><em type="italic">Vestanvik </em>(Storu. V.b.) <em type="italic">Jovjaevrie </em><em type="italic">Joesjö </em>(Storu. V.b.) <em type="italic">Juava </em><em type="italic">Jovan </em>(Storu. V.b.) <em type="italic">Juksjaevrie </em>/SaU Juksjávrrie/ <em type="italic">Juksjaur </em>(Storu. V.b.) <em type="italic">Jyörra </em>/SaU Jyörra/ <em type="italic">Jörn </em>(Jörn V.b.) <em type="italic">Järvarebyjne </em><em type="italic">Järvsjö </em>(Vilh. V.b.) </p>
<p><em type="italic">K Klimhpe </em><em type="italic">Klimpfjäll </em>(Vilh. V.b.) <em type="italic">Knafta </em><em type="italic">Knaften </em>(Lycks. V.b.) <em type="italic">Kraeniesovvene </em>/SaU Krániesuvvane, Guossasuvvane/ <em type="italic">Vindelgransele </em>(Lycks. V.b.) <em type="italic">Krovhtejaevrie </em><em type="italic">Grytsjö </em>(Vilh. V.b.) <em type="italic">Kruehkiejaevrie </em><em type="italic">Hacksjö </em>(Vilh. V.b.) <em type="italic">Kroenije </em><em type="italic">Grönfjäll </em>(Vilh. V.b.) </p>
<p><em type="italic">L Laajnejaevrie </em>/SaU Lájdniejávrrie/ <em type="italic">Lainejaur </em>(Malå V.b.) <em type="italic">Laadtege </em><em type="italic">Latikberg </em>(Vilh. V.b.) <em type="italic">Liksjoe, Liksjsovvene, Liksjsoene </em>/SaU Liksjuo/ <em type="italic">Lycksele </em>(Lycks. V.b.) <em type="italic">Loemenjaevrie </em><em type="italic">Lomsjö </em>(Åsele V.b.) <em type="italic">Lubbsjaevrie </em><em type="italic">Lubbträsk </em>(Storu. V.b.) <em type="italic">Luspie </em>/SaU Lusspie/ <em type="italic">Storuman </em>(Storu. V.b.) <em type="italic">Luvlieloekte </em><em type="italic">Östervik </em>(Storu. V.b.) <em type="italic">Läksjoe </em><em type="italic">Lögda </em>(Åsele V.b.) </p>
<p><em type="italic">M Maalege </em>/SaU Máláge/ <em type="italic">Malå </em>(Malå V.b.) <em type="italic">Malkoemahkie </em><em type="italic">Malgovik </em>(Vilh. V.b.) <em type="italic">Miesiegoejhke </em><em type="italic">Meselfors </em>(Vilh. V.b.) <em type="italic">Mietskehke </em><em type="italic">Röberg </em>(Vilh. V.b.) <em type="italic">Mïetskejaevrie </em><em type="italic">Bäverträsk </em>(Lycks. V.b.) <em type="italic">Mihte </em><em type="italic">Mittådalen </em>(Härje. Jämtl.) <em type="italic">Muerhkie </em><em type="italic">Mårkan </em>(Storu. V.b.) </p>
<p><em type="italic">N Neasna </em><em type="italic">Nästansjö </em>(Vilh. V.b.) <em type="italic">Neassa </em><em type="italic">Tännäs </em>(Härje. Dal.) <em type="italic">Niestie njuenie </em><em type="italic">Lövliden </em>(Vilh. V.b.) <em type="italic">Njoktjenjuenie </em><em type="italic">Svannäs </em>(Vilh. V.b.) <em type="italic">Njoktjhjaevrie </em><em type="italic">Svanabyn </em>(Dor. V.b.) <em type="italic">Nolhpe </em>/SaU Nulppa/ <em type="italic">Nolpen </em>(Sor. V.b.) <em type="italic">Nommehtsjaevrie </em><em type="italic">Näsvattnet </em>(Storu. V.b.) <em type="italic">Nordmelikse, Novlemaanege </em><em type="italic">Nordmaling </em>(Nordm. V.b.) <em type="italic">Nåara </em><em type="italic">Härbergsdalen </em>(Ströms. Jämtl.) <em type="italic">Nåarene </em>/SaU Nuoráne/ <em type="italic">Norsjö </em>(Norsjö V.b.) <em type="italic">Nårhta </em><em type="italic">Nordanås </em>(Åsele V.b.) </p>
<p><em type="italic">O </em><em type="italic">Oksejohke </em><em type="italic">Laxbäcken </em>(Vilh. V.b.) <em type="italic">Onne giemnie, Henten laedtie </em><em type="italic">Henriksfjäll </em>(Vilh. V.b.) <em type="italic">Orrestaare </em><em type="italic">Örnsköldsvik </em>(Ö-vik V.n.) </p>
<p><em type="italic">P </em><em type="italic">Plaajhkije </em>P&gt;&lt;B <em type="italic">Blajkliden </em>(Vilh. V.b.) <em type="italic">Plaavere </em><em type="italic">Blåsjön </em>(Ströms. Jämtl.) <em type="italic">Provhke </em><em type="italic">Ljusnedal </em>(Härje. Jämtl.) </p>
<p><em type="italic">R </em><em type="italic">Raavrhjohke </em><em type="italic">Rönnbäck </em>(Storu. V.b.) <em type="italic">Raevkie </em><em type="italic">Raukasjö </em>(Dor. V.b.) <em type="italic">Rejkanjaevrie </em><em type="italic">Rekansjö </em>(Vilh. V.b.) <em type="italic">Riehkie </em><em type="italic">Tegelträsk </em>(Ö.vik V.n.) <em type="italic">Rïeksh vaartoe </em><em type="italic">Ripfjäll </em>(Storu. V.b.) <em type="italic">Rijsiejohke </em><em type="italic">Risbäck </em>(Dor. V.b.) <em type="italic">Råaskoe </em>/SaU Ruosskuo/ <em type="italic">Rusksele </em>(Lycks. V.b.) <em type="italic">Råava </em>, <em type="italic">Råavoe </em><em type="italic">Råsele </em>(Vilh. V.b.) <em type="italic">Räjmere </em><em type="italic">Remmarn </em>(Ö.vik V.n.) <em type="italic">Rööpsnjuana </em><em type="italic">Rönnäs </em>(Vilh. V.b.) </p>
<p><em type="italic">S Saadteskenjuana </em><em type="italic">Saxnäs </em>(Vilh. V.b.) <em type="italic">Saedtieloekte </em>/SaU Sáddieluoktta/ <em type="italic">Blajken </em>(Storu. V.b.) <em type="italic">Sealma </em><em type="italic">Öravan </em>(Lycks. V.b.) <em type="italic">Sïerkeplueviegielese </em><em type="italic">Rismyrliden </em>(Vilh. V.b.) <em type="italic">Sjïelejaevrie </em><em type="italic">Skälvattnet </em>(Storu. V.b.) <em type="italic">Sjeltie </em><em type="italic">Åsele </em>(Åsele V.b.) <em type="italic">Sjädtavaellie </em><em type="italic">Sundsvall </em>(Sundsv. V.n.) <em type="italic">Skaavtjan jaevrie </em><em type="italic">Skäggvattnet </em>(Storu. V.b.) <em type="italic">Skaalma </em><em type="italic">Skalmodal </em>(Vilh. V.b.) <em type="italic">Skillehte </em>, <em type="italic">Syöldete </em>/SaU Syöldate/ <em type="italic">Skellefteå </em>(Skell. V.b.) <em type="italic">Skärvoe </em><em type="italic">Skarvsjöby </em>(Storu. V.b.) <em type="italic">Skåabpoegaedtie </em><em type="italic">Hansbo </em>(Vilh. V.b.) <em type="italic">Staare </em><em type="italic">Östersund </em>(Östers. Jämtl.) <em type="italic">Stejhka </em>/SaU Steäjkka/ <em type="italic">Malånäs </em>(Malå V.b.) <em type="italic">Stoere Giemnie, Tjiehtele </em><em type="italic">Kittelfjäll </em>(Vilh. V.b.) <em type="italic">Straejmie </em><em type="italic">Strömsund </em>(Ströms. Jämtl.) <em type="italic">Strijmie </em><em type="italic">Strimasund </em>(Storu. V.b.) <em type="italic">Stuehkie </em><em type="italic">Stockholm </em>(Stockh. Stockh.) <em type="italic">Suarsa </em>/SaU Suarssá/ <em type="italic">Sorsele </em>(Sor. V.b.) <em type="italic">Suvhpiesovvene </em><em type="italic">Aspsele </em>(Åsele V.b.) <em type="italic">Såaka </em><em type="italic">Undersåker </em>(Åre Jämtl.) <em type="italic">Såehkie-deava </em>/SaU Såhkie-dievvá/ <em type="italic">Björkbacka </em>(Storu. V.b.) </p>
<p><em type="italic">T Tïene </em><em type="italic">Tjärn </em>(Ö.vik V.n.) <em type="italic">Tjaerhvieåejjie </em><em type="italic">Björkberg </em>(Lycks. V.b.) <em type="italic">Tjarvetje </em><em type="italic">Gävle </em>(Gävle Gävleb.) <em type="italic">Teanndaelie </em><em type="italic">Tänndalen </em>(Härje. Jämtl.) <em type="italic">Tjeedtege </em><em type="italic">Gäddede </em>(Ströms. Jämtl.) <em type="italic">Tjijrie </em><em type="italic">Lövberg </em>(Vilh. V.b.) <em type="italic">Tjoevtjejaevrie </em><em type="italic">Siksjö </em>(Vilh. V.b.) <em type="italic">Tjåelmie </em><em type="italic">Bergsund </em>(Vilh. V.b.) </p>
<p><em type="italic">U Ulliesjaevrie </em><em type="italic">Ullisjaure </em>(Storu. V.b.) <em type="italic">Upmeje </em>/SaU Ubmeje/ <em type="italic">Umeå </em>(Umeå V.b.) </p>
<p><em type="italic">V Vaellienjuana </em><em type="italic">Vallenäs </em>(Storu. V.b.) <em type="italic">Vijriesjaevrie </em><em type="italic">Virisen </em>(Storu. V.b.) <em type="italic">Vistege </em><em type="italic">Fredrika </em>(Bjurh. V.b.) <em type="italic">Vistegentjuvvelge </em><em type="italic">Viskaberg </em>(Åsele V.b.) <em type="italic">Voermese </em><em type="italic">Ormsjö </em>(Dor. V.b.) <em type="italic">Vualkasovvene </em><em type="italic">Volgsele </em>(Vilh. V.b.) <em type="italic">Vualtjere </em><em type="italic">Vilhelmina </em>(Vilh. V.b.) <em type="italic">Vuarnasovvene </em>/SaU Vuordnasuvváne/ <em type="italic">Vormsele </em>(Lycks. V.b.) <em type="italic">Vudtele </em>/SaU Vyöddale/ <em type="italic">Vindeln </em>(Vind. V.b.) </p>
<p><em type="italic">Å Åanghkerenjeeruve </em><em type="italic">Ankarede </em>(Ströms. Jämtl.) <em type="italic">Åarjelmïere </em><em type="italic">Söderhamn </em>(Söderh. Gävleb.) <em type="italic">Åarjel Saedtienjuana </em><em type="italic">Södra Sandnäset </em>(Storu. V.b.) <em type="italic">Ååltohke </em>/SaU Ålduke(jávrrie)/ <em type="italic">Norra Fjällnäs </em>, <em type="italic">Oltoken </em>(Storu. V.b.) </p>
</body></document>
